espresso_ir/__init__.py
espresso_ir/cli.py
espresso_ir/mods/__init__.py
espresso_ir/mods/cloudtrail_api.py
espresso_ir/mods/ec2_snapshot.py
espresso_ir/mods/flow_logs.py
espresso_ir/mods/get_logs.py
espresso_ir/mods/memdump.py
espresso_ir/mods/s3_bucket_cloudtrail.py
espresso_ir/mods/s3_buckets_ir.py
espresso_ir/mods/ssm_setup.py
espresso_ir/mods/vpc.py
espresso_ir-0.0.2.dist-info/LICENSE.txt
espresso_ir-0.0.2.dist-info/METADATA
espresso_ir-0.0.2.dist-info/WHEEL
espresso_ir-0.0.2.dist-info/entry_points.txt
espresso_ir-0.0.2.dist-info/top_level.txt
espresso_ir-0.0.2.dist-info/RECORD
