Metadata-Version: 2.1
Name: espresso-ir
Version: 0.0.2
Summary: IR tool for acquiring memory images from windows EC2 instances on AWS
Home-page: https://github.com/terrizmo/espresso_ir
Author: Terrizmo
Author-email: espressoir@outlook.com
License: UNKNOWN
Platform: UNKNOWN
Classifier: Programming Language :: Python :: 3
Classifier: License :: OSI Approved :: MIT License
Classifier: Operating System :: OS Independent
Classifier: Development Status :: 3 - Alpha
Classifier: Intended Audience :: Developers
Classifier: Intended Audience :: Information Technology
Classifier: Intended Audience :: Science/Research
Classifier: Intended Audience :: System Administrators
Classifier: Environment :: Console
Classifier: Natural Language :: English
Classifier: Programming Language :: Python :: 3.7
Classifier: Topic :: Security
Requires-Python: >=3.7
Requires-Dist: awscli (==1.18.154)
Requires-Dist: boto3 (==1.15.13)
Requires-Dist: botocore (==1.18.13)
